nptp/__init__.py
nptp/app_error.log
nptp/car.jpg
nptp/cli.py
nptp/empty.txt
nptp/lorem500.txt
nptp/readonly.txt
nptp-0.1.0.dist-info/METADATA
nptp-0.1.0.dist-info/WHEEL
nptp-0.1.0.dist-info/entry_points.txt
nptp-0.1.0.dist-info/RECORD
