Metadata-Version: 2.1
Name: nptp
Version: 0.1.0
Summary: A command-line tool to calculate file statistics.
Author: Naisarg Jiteshkumar Patel
Author-email: 24043250@saultcollege.ca
Requires-Python: >=3.9,<4.0
Classifier: Programming Language :: Python :: 3
Classifier: Programming Language :: Python :: 3.9
Classifier: Programming Language :: Python :: 3.10
Classifier: Programming Language :: Python :: 3.11
Classifier: Programming Language :: Python :: 3.12
Classifier: Programming Language :: Python :: 3.13
